netsse/__init__.py
netsse/base.py
netsse/analys/__init__.py
netsse/analys/buoy.py
netsse/analys/dsa.py
netsse/analys/emep.py
netsse/analys/enc_spec.py
netsse/analys/sawb.py
netsse/analys/spec.py
netsse/model/__init__.py
netsse/model/bathymetry.py
netsse/model/envir_cond.py
netsse/model/era5.py
netsse/model/ship.py
netsse/simul/__init__.py
netsse/simul/ship_resp.py
netsse/tools/__init__.py
netsse/tools/misc_func.py
netsse/tools/viz.py
netsse-2.1.0.dist-info/METADATA
netsse-2.1.0.dist-info/WHEEL
netsse-2.1.0.dist-info/licenses/LICENCE.md
netsse-2.1.0.dist-info/RECORD
