Metadata-Version: 2.4
Name: netsse
Version: 2.1.0
Summary: NetSSE Python package for network-based sea state estimation
Project-URL: Repository, https://gitlab.gbar.dtu.dk/regmo/NetSSE
Project-URL: Documentation, https://netsse.readthedocs.io/en/latest/
Project-URL: DOI, https://doi.org/10.11583/DTU.26379811
Author-email: "Raphael E.G. Mounet" <regmo@dtu.dk>, "Ulrik D. Nielsen" <udni@dtu.dk>
Maintainer-email: "Raphael E.G. Mounet" <regmo@dtu.dk>
License:                     GNU GENERAL PUBLIC LICENSE
License-File: LICENCE.md
Keywords: in-situ observation,physical oceanography,sea spectrum,ship technology,wave estimation
Classifier: Development Status :: 3 - Alpha
Classifier: Intended Audience :: Science/Research
Classifier: License :: OSI Approved :: GNU General Public License v3 (GPLv3)
Classifier: Natural Language :: English
Classifier: Operating System :: OS Independent
Classifier: Programming Language :: Python :: 3
Classifier: Topic :: Scientific/Engineering :: Oceanography
Requires-Python: >=3.12
Requires-Dist: cartopy>=0.24.1
Requires-Dist: cdsapi>=0.7.5
Requires-Dist: geopy>=2.4.1
Requires-Dist: matplotlib>=3.8.4
Requires-Dist: numpy>=2.0.0
Requires-Dist: scipy>=1.14.0
